Metadata-Version: 2.1
Name: abstract-server
Version: 0.0.0.5
Summary: abstract_server
Home-page: https://github.com/AbstractEndeavors/abstract_server
Author: putkoff
Author-email: partners@abstractendeavors.com
Classifier: Development Status :: 3 - Alpha
Classifier: Intended Audience :: Developers
Classifier: License :: OSI Approved :: MIT License
Classifier: Programming Language :: Python :: 3
Classifier: Programming Language :: Python :: 3.11
Requires-Python: >=3.6
License-File: LICENSE
